ApiEngine/BaseCase.py
ApiEngine/__init__.py
ApiEngine/caseLog.py
ApiEngine/core.py
ApiEngine/dbClient.py
ApiEngine/global_func.py
ApiEngine/testResult.py
api_engine_xin-0.0.8.dist-info/licenses/LICENSE
api_engine_xin-0.0.8.dist-info/METADATA
api_engine_xin-0.0.8.dist-info/WHEEL
api_engine_xin-0.0.8.dist-info/top_level.txt
api_engine_xin-0.0.8.dist-info/RECORD
